torchiteration/__init__.py
torchiteration/hparams.py
torchiteration/iterate.py
torchiteration/steps.py
torchiteration-0.0.5.dist-info/licenses/LICENSE
torchiteration-0.0.5.dist-info/METADATA
torchiteration-0.0.5.dist-info/WHEEL
torchiteration-0.0.5.dist-info/top_level.txt
torchiteration-0.0.5.dist-info/zip-safe
torchiteration-0.0.5.dist-info/RECORD
