Metadata-Version: 2.4
Name: torchiteration
Version: 0.0.5
Home-page: https://github.com/cat-claws/torchiteration
Author: cat-claws
Author-email: 47313357+cat-claws@users.noreply.github.com
License: MIT
Classifier: Programming Language :: Python
Classifier: Programming Language :: Python :: 3
License-File: LICENSE
Requires-Dist: numpy
Requires-Dist: pandas
Dynamic: author
Dynamic: author-email
Dynamic: classifier
Dynamic: description
Dynamic: description-content-type
Dynamic: home-page
Dynamic: license
Dynamic: license-file
Dynamic: requires-dist
